{
    "nombre_repo": "Nombre del repositorio",
    "org_or_user_github": "Usuario de GitHub u Organizacion del repo",
    "cfn_stack": "Nombre del stack en AWS",
    "project": "Identificador del proyecto",
    "DEV_ARN_SSM_KMS": "Llave multiregion para Parameter Store. DEV",
    "DEV_ARN_DYNAMODB_KMS": "Llave multiregion para DynamoDB. DEV",
    "DEV_ARN_SSM_KMS_DR": "Llave multiregion para Parameter Store. DR. DEV",
    "DEV_ARN_DYNAMODB_KMS_DR": "Llave multiregion para DynamoDB. DR. DEV",
    "PROD_ARN_SSM_KMS": "Llave multiregion para Parameter Store. PROD",
    "PROD_ARN_DYNAMODB_KMS": "Llave multiregion para DynamoDB. PROD",
    "PROD_ARN_SSM_KMS_DR": "Llave multiregion para Parameter Store. DR. PROD",
    "PROD_ARN_DYNAMODB_KMS_DR": "Llave multiregion para DynamoDB. DR. PROD",
    "sam_container": "public.ecr.aws/sam/build-python3.8:1.32.0",
    "sam_bucket": "Nombre del bucket para SAM",
    "DEV_secret_aws_key_id": "DEV_AWS_KEY_ID",
    "DEV_secret_aws_key_secret": "DEV_AWS_KEY_SECRET",
    "DEV_secret_aws_account_id": "DEV_AWS_ACCOUNT_ID",
    "PROD_secret_aws_key_id": "PROD_AWS_KEY_ID",
    "PROD_secret_aws_key_secret": "PROD_AWS_KEY_SECRET",
    "PROD_secret_aws_account_id": "PROD_AWS_ACCOUNT_ID",    
    "_copy_without_render": [
        ".cz.yaml"
    ]
    
}
